air/__init__.py
air/experiment.py
air/io.py
air/task.py
air/types.py
air/tests/__init__.py
air/tests/test_io.py
air/tests/test_task.py
air52-0.0.6.dist-info/LICENSE
air52-0.0.6.dist-info/WHEEL
air52-0.0.6.dist-info/METADATA
air52-0.0.6.dist-info/RECORD
