Metadata-Version: 2.1
Name: air52
Version: 0.0.6
Summary: Air.
Home-page: https://github.com/Yura52/air
License: UNKNOWN
Keywords: library, python
Author: Yura52
Author-email: strausmg@gmail.com
Requires-Python: >=3.7
Classifier: Intended Audience :: Developers
Classifier: License :: OSI Approved :: MIT License
Classifier: Operating System :: MacOS
Classifier: Operating System :: Unix
Classifier: Programming Language :: Python :: 3
